moldflow/__init__.py
moldflow/animation_export_options.py
moldflow/boundary_conditions.py
moldflow/boundary_list.py
moldflow/cad_diagnostic.py
moldflow/cad_manager.py
moldflow/circuit_generator.py
moldflow/com_proxy.py
moldflow/common.py
moldflow/constants.py
moldflow/data_transform.py
moldflow/diagnosis_manager.py
moldflow/double_array.py
moldflow/ent_list.py
moldflow/errors.py
moldflow/exceptions.py
moldflow/folder_manager.py
moldflow/helper.py
moldflow/i18n.py
moldflow/image_export_options.py
moldflow/import_options.py
moldflow/integer_array.py
moldflow/layer_manager.py
moldflow/localization.py
moldflow/logger.py
moldflow/material_finder.py
moldflow/material_plot.py
moldflow/material_selector.py
moldflow/mesh_editor.py
moldflow/mesh_generator.py
moldflow/mesh_summary.py
moldflow/message_box.py
moldflow/model_duplicator.py
moldflow/modeler.py
moldflow/mold_surface_generator.py
moldflow/plot.py
moldflow/plot_manager.py
moldflow/predicate.py
moldflow/predicate_manager.py
moldflow/project.py
moldflow/prop.py
moldflow/property_editor.py
moldflow/runner_generator.py
moldflow/server.py
moldflow/string_array.py
moldflow/study_doc.py
moldflow/synergy.py
moldflow/system_message.py
moldflow/unit_conversion.py
moldflow/user_plot.py
moldflow/vector.py
moldflow/vector_array.py
moldflow/version.json
moldflow/version_check.py
moldflow/viewer.py
moldflow/locale/__init__.py
moldflow/locale/de-DE/LC_MESSAGES/locale.de-DE.mo
moldflow/locale/en-US/LC_MESSAGES/locale.en-US.mo
moldflow/locale/es-ES/LC_MESSAGES/locale.es-ES.mo
moldflow/locale/fr-FR/LC_MESSAGES/locale.fr-FR.mo
moldflow/locale/it-IT/LC_MESSAGES/locale.it-IT.mo
moldflow/locale/ja-JP/LC_MESSAGES/locale.ja-JP.mo
moldflow/locale/ko-KR/LC_MESSAGES/locale.ko-KR.mo
moldflow/locale/pt-PT/LC_MESSAGES/locale.pt-PT.mo
moldflow/locale/zh-CN/LC_MESSAGES/locale.zh-CN.mo
moldflow/locale/zh-TW/LC_MESSAGES/locale.zh-TW.mo
moldflow-27.0.0.dist-info/licenses/LICENSE
moldflow-27.0.0.dist-info/licenses/THIRD_PARTY_NOTICES.md
moldflow-27.0.0.dist-info/METADATA
moldflow-27.0.0.dist-info/WHEEL
moldflow-27.0.0.dist-info/top_level.txt
moldflow-27.0.0.dist-info/RECORD
