Metadata-Version: 2.4
Name: moldflow
Version: 27.0.0
Summary: Moldflow API Library
Home-page: https://github.com/Autodesk/moldflow-api
Author: Autodesk Inc.
License: Apache-2.0
Project-URL: Documentation, https://autodesk.github.io/moldflow-api
Project-URL: Source, https://github.com/Autodesk/moldflow-api
Project-URL: Issues, https://github.com/Autodesk/moldflow-api/issues
Project-URL: Security, https://www.autodesk.com/trust/security/vulnerability-disclosure-policy
Keywords: moldflow,autodesk,cae,simulation,manufacturing,injection molding,plastic injection,analysis,automation,api,synergy
Classifier: Development Status :: 5 - Production/Stable
Classifier: Intended Audience :: Manufacturing
Classifier: Intended Audience :: Science/Research
Classifier: Operating System :: Microsoft :: Windows
Classifier: Programming Language :: Python :: 3
Classifier: Programming Language :: Python :: 3.10
Classifier: Programming Language :: Python :: 3.11
Classifier: Programming Language :: Python :: 3.12
Classifier: Programming Language :: Python :: 3.13
Classifier: Programming Language :: Python :: 3.14
Classifier: Topic :: Scientific/Engineering
Classifier: Topic :: Software Development :: Libraries :: Python Modules
Requires-Python: <3.15,>=3.10
License-File: LICENSE
License-File: THIRD_PARTY_NOTICES.md
Requires-Dist: pywin32==311; platform_system == "Windows"
Dynamic: license-file
